aiondtech/__init__.py
aiondtech/client.py
aiondtech/models.py
aiondtech/py.typed
aiondtech-2.0.0.dist-info/licenses/LICENSE
aiondtech-2.0.0.dist-info/METADATA
aiondtech-2.0.0.dist-info/WHEEL
aiondtech-2.0.0.dist-info/top_level.txt
aiondtech-2.0.0.dist-info/RECORD
