Metadata-Version: 2.4
Name: aiondtech
Version: 2.0.0
Summary: Official Python SDK for AiondTech Resume Analyser API
Author-email: AiondTech <support@aiondtech.com>
Maintainer-email: AiondTech <support@aiondtech.com>
License: MIT
Project-URL: Homepage, https://aiondtech.com
Project-URL: Documentation, https://docs.aiondtech.com
Project-URL: Repository, https://github.com/aiondtech/aiondtech-python
Project-URL: Bug Tracker, https://github.com/aiondtech/aiondtech-python/issues
Project-URL: Changelog, https://github.com/aiondtech/aiondtech-python/blob/main/CHANGELOG.md
Keywords: aiondtech,resume,cv,parser,analyzer,ats,recruitment,hr,api,sdk
Classifier: Development Status :: 5 - Production/Stable
Classifier: Intended Audience :: Developers
Classifier: License :: OSI Approved :: MIT License
Classifier: Operating System :: OS Independent
Classifier: Programming Language :: Python :: 3
Classifier: Programming Language :: Python :: 3.8
Classifier: Programming Language :: Python :: 3.9
Classifier: Programming Language :: Python :: 3.10
Classifier: Programming Language :: Python :: 3.11
Classifier: Programming Language :: Python :: 3.12
Classifier: Topic :: Software Development :: Libraries :: Python Modules
Classifier: Topic :: Office/Business :: Financial :: Spreadsheet
Requires-Python: >=3.8
License-File: LICENSE
Requires-Dist: requests>=2.25.0
Provides-Extra: dev
Requires-Dist: pytest>=7.0.0; extra == "dev"
Requires-Dist: pytest-cov>=4.0.0; extra == "dev"
Requires-Dist: black>=23.0.0; extra == "dev"
Requires-Dist: mypy>=1.0.0; extra == "dev"
Dynamic: license-file
